[{"title":"Абаза","region":"Республика Хакасия","size":17111},{"title":"Абакан","region":"Республика Хакасия","size":165183},{"title":"Абдулино","region":"Оренбургская область","size":20663},{"title":"Абинск","region":"Краснодарский край","size":34926},{"title":"Агидель","region":"Республика Башкортостан","size":16365},{"title":"Агрыз","region":"Республика Татарстан","size":19299},{"title":"Адыгейск","region":"Республика Адыгея","size":12689},{"title":"Азнакаево","region":"Республика Татарстан","size":34859},{"title":"Азов","region":"Ростовская область","size":82882},{"title":"Ак-Довурак","region":"Республика Тыва","size":13469},{"title":"Аксай","region":"Ростовская область","size":41984},{"title":"Алагир","region":"Республика Северная Осетия - Алания","size":20949},{"title":"Алапаевск","region":"Свердловская область","size":38198},{"title":"Алатырь","region":"Республика Чувашия","size":38202},{"title":"Алдан","region":"Республика Якутия","size":21277},{"title":"Алейск","region":"Алтайский край","size":28528},{"title":"Александров","region":"Владимирская область","size":61544},{"title":"Александровск","region":"Пермский край","size":15022},{"title":"Александровск-Сахалинский","region":"Сахалинская область","size":10613},{"title":"Алексеевка","region":"Белгородская область","size":39026},{"title":"Алексин","region":"Тульская область","size":61738},{"title":"Алзамай","region":"Иркутская область","size":6751},{"title":"Алупка","region":"Республика Крым","size":8497},{"title":"Алушта","region":"Республика Крым","size":28642},{"title":"Альметьевск","region":"Республика Татарстан","size":146309},{"title":"Амурск","region":"Хабаровский край","size":42977},{"title":"Анадырь","region":"Чукотский АО","size":13053},{"title":"Анапа","region":"Краснодарский край","size":58983},{"title":"Ангарск","region":"Иркутская область","size":233765},{"title":"Андреаполь","region":"Тверская область","size":8265},{"title":"Анжеро-Судженск","region":"Кемеровская область","size":76669},{"title":"Анива","region":"Сахалинская область","size":8449},{"title":"Апатиты","region":"Мурманская область","size":59690},{"title":"Апрелевка","region":"Московская область","size":18467},{"title":"Апшеронск","region":"Краснодарский край","size":40229},{"title":"Арамиль","region":"Свердловская область","size":14227},{"title":"Аргун","region":"Республика Чечня","size":29528},{"title":"Ардатов","region":"Республика Мордовия","size":9400},{"title":"Ардон","region":"Республика Северная Осетия - Алания","size":18774},{"title":"Арзамас","region":"Нижегородская область","size":106367},{"title":"Аркадак","region":"Саратовская область","size":12846},{"title":"Армавир","region":"Краснодарский край","size":188897},{"title":"Армянск","region":"Республика Крым","size":22468},{"title":"Арсеньев","region":"Приморский край","size":56742},{"title":"Арск","region":"Республика Татарстан","size":18114},{"title":"Артём","region":"Приморский край","size":102636},{"title":"Артёмовск","region":"Красноярский край","size":2180},{"title":"Артёмовский","region":"Свердловская область","size":32878},{"title":"Архангельск","region":"Архангельская область","size":348716},{"title":"Асбест","region":"Свердловская область","size":70067},{"title":"Асино","region":"Томская область","size":25614},{"title":"Астрахань","region":"Астраханская область","size":520662},{"title":"Аткарск","region":"Саратовская область","size":25620},{"title":"Ахтубинск","region":"Астраханская область","size":41898},{"title":"Ачинск","region":"Красноярский край","size":109156},{"title":"Аша","region":"Челябинская область","size":31916},{"title":"Бабаево","region":"Вологодская область","size":12074},{"title":"Бабушкин","region":"Республика Бурятия","size":4542},{"title":"Бавлы","region":"Республика Татарстан","size":22109},{"title":"Багратионовск","region":"Калининградская область","size":6399},{"title":"Байкальск","region":"Иркутская область","size":13589},{"title":"Баймак","region":"Республика Башкортостан","size":17710},{"title":"Бакал","region":"Челябинская область","size":20953},{"title":"Баксан","region":"Республика Кабардино-Балкария","size":36857},{"title":"Балабаново","region":"Калужская область","size":26337},{"title":"Балаково","region":"Саратовская область","size":199576},{"title":"Балахна","region":"Нижегородская область","size":51526},{"title":"Балашиха","region":"Московская область","size":215353},{"title":"Балашов","region":"Саратовская область","size":82222},{"title":"Балей","region":"Забайкальский край","size":12536},{"title":"Балтийск","region":"Калининградская область","size":32670},{"title":"Барабинск","region":"Новосибирская область","size":30250},{"title":"Барнаул","region":"Алтайский край","size":635585},{"title":"Барыш","region":"Ульяновская область","size":17149},{"title":"Батайск","region":"Ростовская область","size":112400},{"title":"Бахчисарай","region":"Республика Крым","size":26363},{"title":"Бежецк","region":"Тверская область","size":24517},{"title":"Белая Калитва","region":"Ростовская область","size":43688},{"title":"Белая Холуница","region":"Кировская область","size":11232},{"title":"Белгород","region":"Белгородская область","size":356426},{"title":"Белебей","region":"Республика Башкортостан","size":60183},{"title":"Белёв","region":"Тульская область","size":13918},{"title":"Белинский","region":"Пензенская область","size":8567},{"title":"Белово","region":"Кемеровская область","size":76752},{"title":"Белогорск","region":"Амурская область","size":68220},{"title":"Белогорск","region":"Республика Крым","size":18199},{"title":"Белозерск","region":"Вологодская область","size":9614},{"title":"Белокуриха","region":"Алтайский край","size":15072},{"title":"Беломорск","region":"Республика Карелия","size":11217},{"title":"Белорецк","region":"Республика Башкортостан","size":68804},{"title":"Белореченск","region":"Краснодарский край","size":53891},{"title":"Белоусово","region":"Калужская область","size":8432},{"title":"Белоярский","region":"Ханты-Мансийский АО — Югра","size":20283},{"title":"Белый","region":"Тверская область","size":3771},{"title":"Бердск","region":"Новосибирская область","size":98809},{"title":"Березники","region":"Пермский край","size":156350},{"title":"Берёзовский","region":"Кемеровская область","size":47292},{"title":"Берёзовский","region":"Свердловская область","size":51583},{"title":"Беслан","region":"Республика Северная Осетия - Алания","size":36724},{"title":"Бийск","region":"Алтайский край","size":203826},{"title":"Бикин","region":"Хабаровский край","size":17156},{"title":"Билибино","region":"Чукотский АО","size":5504},{"title":"Биробиджан","region":"Еврейская АО","size":75419},{"title":"Бирск","region":"Республика Башкортостан","size":41637},{"title":"Бирюсинск","region":"Иркутская область","size":8981},{"title":"Бирюч","region":"Белгородская область","size":7842},{"title":"Благовещенск","region":"Республика Башкортостан","size":34246},{"title":"Благовещенск","region":"Амурская область","size":214397},{"title":"Благодарный","region":"Ставропольский край","size":32736},{"title":"Бобров","region":"Воронежская область","size":19738},{"title":"Богданович","region":"Свердловская область","size":31752},{"title":"Богородицк","region":"Тульская область","size":31897},{"title":"Богородск","region":"Нижегородская область","size":25497},{"title":"Боготол","region":"Красноярский край","size":21029},{"title":"Богучар","region":"Воронежская область","size":11811},{"title":"Бодайбо","region":"Иркутская область","size":15331},{"title":"Бокситогорск","region":"Ленинградская область","size":16593},{"title":"Болгар","region":"Республика Татарстан","size":8650},{"title":"Бологое","region":"Тверская область","size":23499},{"title":"Болотное","region":"Новосибирская область","size":16969},{"title":"Болохово","region":"Тульская область","size":9619},{"title":"Болхов","region":"Орловская область","size":11421},{"title":"Большой Камень","region":"Приморский край","size":39257},{"title":"Бор","region":"Нижегородская область","size":78079},{"title":"Борзя","region":"Забайкальский край","size":31376},{"title":"Борисоглебск","region":"Воронежская область","size":65585},{"title":"Боровичи","region":"Новгородская область","size":54731},{"title":"Боровск","region":"Калужская область","size":12283},{"title":"Бородино","region":"Красноярский край","size":17423},{"title":"Братск","region":"Иркутская область","size":246348},{"title":"Бронницы","region":"Московская область","size":21102},{"title":"Брянск","region":"Брянская область","size":415640},{"title":"Бугульма","region":"Республика Татарстан","size":89144},{"title":"Бугуруслан","region":"Оренбургская область","size":52249},{"title":"Будённовск","region":"Ставропольский край","size":64628},{"title":"Бузулук","region":"Оренбургская область","size":82816},{"title":"Буинск","region":"Республика Татарстан","size":20342},{"title":"Буй","region":"Костромская область","size":25763},{"title":"Буйнакск","region":"Республика Дагестан","size":65735},{"title":"Бутурлиновка","region":"Воронежская область","size":27208},{"title":"Валдай","region":"Новгородская область","size":16099},{"title":"Валуйки","region":"Белгородская область","size":35322},{"title":"Велиж","region":"Смоленская область","size":7620},{"title":"Великие Луки","region":"Псковская область","size":98778},{"title":"Великий Новгород","region":"Новгородская область","size":218724},{"title":"Великий Устюг","region":"Вологодская область","size":31664},{"title":"Вельск","region":"Архангельская область","size":23885},{"title":"Венёв","region":"Тульская область","size":15220},{"title":"Верещагино","region":"Пермский край","size":22760},{"title":"Верея","region":"Московская область","size":5368},{"title":"Верхнеуральск","region":"Челябинская область","size":9459},{"title":"Верхний Тагил","region":"Свердловская область","size":11843},{"title":"Верхний Уфалей","region":"Челябинская область","size":30504},{"title":"Верхняя Пышма","region":"Свердловская область","size":58707},{"title":"Верхняя Салда","region":"Свердловская область","size":46240},{"title":"Верхняя Тура","region":"Свердловская область","size":9468},{"title":"Верхотурье","region":"Свердловская область","size":8815},{"title":"Верхоянск","region":"Республика Якутия","size":1311},{"title":"Весьегонск","region":"Тверская область","size":7330},{"title":"Ветлуга","region":"Нижегородская область","size":8956},{"title":"Видное","region":"Московская область","size":56798},{"title":"Вилюйск","region":"Республика Якутия","size":10233},{"title":"Вилючинск","region":"Камчатский край","size":22905},{"title":"Вихоревка","region":"Иркутская область","size":22528},{"title":"Вичуга","region":"Ивановская область","size":37609},{"title":"Владивосток","region":"Приморский край","size":592069},{"title":"Владикавказ","region":"Республика Северная Осетия - Алания","size":311635},{"title":"Владимир","region":"Владимирская область","size":348256},{"title":"Волгоград","region":"Волгоградская область","size":1021244},{"title":"Волгодонск","region":"Ростовская область","size":170621},{"title":"Волгореченск","region":"Костромская область","size":17108},{"title":"Волжск","region":"Республика Марий Эл","size":55671},{"title":"Волжский","region":"Волгоградская область","size":314436},{"title":"Вологда","region":"Вологодская область","size":301642},{"title":"Володарск","region":"Нижегородская область","size":9924},{"title":"Волоколамск","region":"Московская область","size":23386},{"title":"Волосово","region":"Ленинградская область","size":12162},{"title":"Волхов","region":"Ленинградская область","size":47344},{"title":"Волчанск","region":"Свердловская область","size":10008},{"title":"Вольск","region":"Саратовская область","size":66520},{"title":"Воркута","region":"Республика Коми","size":70551},{"title":"Воронеж","region":"Воронежская область","size":889680},{"title":"Ворсма","region":"Нижегородская область","size":11622},{"title":"Воскресенск","region":"Московская область","size":91301},{"title":"Воткинск","region":"Республика Удмуртия","size":100034},{"title":"Всеволожск","region":"Ленинградская область","size":59689},{"title":"Вуктыл","region":"Республика Коми","size":12357},{"title":"Выборг","region":"Ленинградская область","size":80013},{"title":"Выкса","region":"Нижегородская область","size":56196},{"title":"Высоковск","region":"Московская область","size":10642},{"title":"Высоцк","region":"Ленинградская область","size":1244},{"title":"Вытегра","region":"Вологодская область","size":10490},{"title":"Вышний Волочёк","region":"Тверская область","size":52326},{"title":"Вяземский","region":"Хабаровский край","size":14556},{"title":"Вязники","region":"Владимирская область","size":41252},{"title":"Вязьма","region":"Смоленская область","size":57103},{"title":"Вятские Поляны","region":"Кировская область","size":35159},{"title":"Гаврилов Посад","region":"Ивановская область","size":6434},{"title":"Гаврилов-Ям","region":"Ярославская область","size":17792},{"title":"Гагарин","region":"Смоленская область","size":31721},{"title":"Гаджиево","region":"Мурманская область","size":11089},{"title":"Гай","region":"Оренбургская область","size":38302},{"title":"Галич","region":"Костромская область","size":17346},{"title":"Гатчина","region":"Ленинградская область","size":92566},{"title":"Гвардейск","region":"Калининградская область","size":13888},{"title":"Гдов","region":"Псковская область","size":4379},{"title":"Геленджик","region":"Краснодарский край","size":54813},{"title":"Георгиевск","region":"Ставропольский край","size":72126},{"title":"Глазов","region":"Республика Удмуртия","size":95835},{"title":"Голицыно","region":"Московская область","size":17447},{"title":"Горбатов","region":"Нижегородская область","size":2278},{"title":"Горно-Алтайск","region":"Республика Алтай","size":62861},{"title":"Горнозаводск","region":"Пермский край","size":12334},{"title":"Горняк","region":"Алтайский край","size":13040},{"title":"Городец","region":"Нижегородская область","size":30699},{"title":"Городище","region":"Пензенская область","size":8102},{"title":"Городовиковск","region":"Республика Калмыкия","size":9565},{"title":"Гороховец","region":"Владимирская область","size":14015},{"title":"Горячий Ключ","region":"Краснодарский край","size":30093},{"title":"Грайворон","region":"Белгородская область","size":6234},{"title":"Гремячинск","region":"Пермский край","size":11005},{"title":"Грозный","region":"Республика Чечня","size":271596},{"title":"Грязи","region":"Липецкая область","size":46798},{"title":"Грязовец","region":"Вологодская область","size":15528},{"title":"Губаха","region":"Пермский край","size":27544},{"title":"Губкин","region":"Белгородская область","size":88562},{"title":"Губкинский","region":"Ямало-Ненецкий АО","size":23340},{"title":"Гудермес","region":"Республика Чечня","size":45643},{"title":"Гуково","region":"Ростовская область","size":67268},{"title":"Гулькевичи","region":"Краснодарский край","size":35225},{"title":"Гурьевск","region":"Калининградская область","size":12433},{"title":"Гурьевск","region":"Кемеровская область","size":24816},{"title":"Гусев","region":"Калининградская область","size":28260},{"title":"Гусиноозёрск","region":"Республика Бурятия","size":23280},{"title":"Гусь-Хрустальный","region":"Владимирская область","size":60773},{"title":"Давлеканово","region":"Республика Башкортостан","size":24040},{"title":"Дагестанские Огни","region":"Республика Дагестан","size":30671},{"title":"Далматово","region":"Курганская область","size":13913},{"title":"Дальнегорск","region":"Приморский край","size":37503},{"title":"Дальнереченск","region":"Приморский край","size":27601},{"title":"Данилов","region":"Ярославская область","size":15861},{"title":"Данков","region":"Липецкая область","size":21056},{"title":"Дегтярск","region":"Свердловская область","size":15521},{"title":"Дедовск","region":"Московская область","size":29280},{"title":"Демидов","region":"Смоленская область","size":7333},{"title":"Дербент","region":"Республика Дагестан","size":119961},{"title":"Десногорск","region":"Смоленская область","size":29677},{"title":"Джанкой","region":"Республика Крым","size":35700},{"title":"Дзержинск","region":"Нижегородская область","size":240762},{"title":"Дзержинский","region":"Московская область","size":47125},{"title":"Дивногорск","region":"Красноярский край","size":28271},{"title":"Дигора","region":"Республика Северная Осетия - Алания","size":10856},{"title":"Димитровград","region":"Ульяновская область","size":122549},{"title":"Дмитриев","region":"Курская область","size":7721},{"title":"Дмитров","region":"Московская область","size":61454},{"title":"Дмитровск","region":"Орловская область","size":5956},{"title":"Дно","region":"Псковская область","size":9061},{"title":"Добрянка","region":"Пермский край","size":35720},{"title":"Долгопрудный","region":"Московская область","size":90976},{"title":"Долинск","region":"Сахалинская область","size":12200},{"title":"Домодедово","region":"Московская область","size":96123},{"title":"Донецк","region":"Ростовская область","size":50085},{"title":"Донской","region":"Тульская область","size":64561},{"title":"Дорогобуж","region":"Смоленская область","size":10720},{"title":"Дрезна","region":"Московская область","size":11815},{"title":"Дубна","region":"Московская область","size":70569},{"title":"Дубовка","region":"Волгоградская область","size":14345},{"title":"Дудинка","region":"Красноярский край","size":22207},{"title":"Духовщина","region":"Смоленская область","size":4370},{"title":"Дюртюли","region":"Республика Башкортостан","size":31272},{"title":"Дятьково","region":"Брянская область","size":29438},{"title":"Евпатория","region":"Республика Крым","size":106840},{"title":"Егорьевск","region":"Московская область","size":70133},{"title":"Ейск","region":"Краснодарский край","size":87771},{"title":"Екатеринбург","region":"Свердловская область","size":1377738,"stations":["Ботаническая","Геологическая","Динамо","Машиностроителей","Площадь 1905 года","Пр-т Космонавтов","Уралмаш","Уральская","Чкаловская"]},{"title":"Елабуга","region":"Республика Татарстан","size":70750},{"title":"Елец","region":"Липецкая область","size":108404},{"title":"Елизово","region":"Камчатский край","size":39548},{"title":"Ельня","region":"Смоленская область","size":10095},{"title":"Еманжелинск","region":"Челябинская область","size":30218},{"title":"Емва","region":"Республика Коми","size":14574},{"title":"Енисейск","region":"Красноярский край","size":18769},{"title":"Ермолино","region":"Калужская область","size":10409},{"title":"Ершов","region":"Саратовская область","size":21447},{"title":"Ессентуки","region":"Ставропольский край","size":100969},{"title":"Ефремов","region":"Тульская область","size":42350},{"title":"Железноводск","region":"Ставропольский край","size":24496},{"title":"Железногорск","region":"Красноярский край","size":85559},{"title":"Железногорск","region":"Курская область","size":95057},{"title":"Железногорск-Илимский","region":"Иркутская область","size":26134},{"title":"Жердевка","region":"Тамбовская область","size":15211},{"title":"Жигулёвск","region":"Самарская область","size":57565},{"title":"Жиздра","region":"Калужская область","size":5585},{"title":"Жирновск","region":"Волгоградская область","size":16890},{"title":"Жуков","region":"Калужская область","size":12150},{"title":"Жуковка","region":"Брянская область","size":18269},{"title":"Жуковский","region":"Московская область","size":102729},{"title":"Завитинск","region":"Амурская область","size":11481},{"title":"Заводоуковск","region":"Тюменская область","size":25657},{"title":"Заволжск","region":"Ивановская область","size":12045},{"title":"Заволжье","region":"Нижегородская область","size":40265},{"title":"Задонск","region":"Липецкая область","size":9695},{"title":"Заинск","region":"Республика Татарстан","size":41798},{"title":"Закаменск","region":"Республика Бурятия","size":11249},{"title":"Заозёрный","region":"Красноярский край","size":10683},{"title":"Заозёрск","region":"Мурманская область","size":11206},{"title":"Западная Двина","region":"Тверская область","size":9376},{"title":"Заполярный","region":"Мурманская область","size":15835},{"title":"Зарайск","region":"Московская область","size":24648},{"title":"Заречный","region":"Пензенская область","size":63579},{"title":"Заречный","region":"Свердловская область","size":26803},{"title":"Заринск","region":"Алтайский край","size":47035},{"title":"Звенигово","region":"Республика Марий Эл","size":11945},{"title":"Звенигород","region":"Московская область","size":16395},{"title":"Зверево","region":"Ростовская область","size":22416},{"title":"Зеленогорск","region":"Красноярский край","size":66018},{"title":"Зеленоградск","region":"Калининградская область","size":13015},{"title":"Зеленодольск","region":"Республика Татарстан","size":97651},{"title":"Зеленокумск","region":"Ставропольский край","size":35790},{"title":"Зерноград","region":"Ростовская область","size":26850},{"title":"Зея","region":"Амурская область","size":25042},{"title":"Зима","region":"Иркутская область","size":32522},{"title":"Златоуст","region":"Челябинская область","size":174985},{"title":"Злынка","region":"Брянская область","size":5507},{"title":"Змеиногорск","region":"Алтайский край","size":10569},{"title":"Знаменск","region":"Астраханская область","size":29357},{"title":"Зубцов","region":"Тверская область","size":6937},{"title":"Зуевка","region":"Кировская область","size":11198},{"title":"Ивангород","region":"Ленинградская область","size":9797},{"title":"Иваново","region":"Ивановская область","size":409277},{"title":"Ивантеевка","region":"Московская область","size":58594},{"title":"Ивдель","region":"Свердловская область","size":17764},{"title":"Игарка","region":"Красноярский край","size":6183},{"title":"Ижевск","region":"Республика Удмуртия","size":628117},{"title":"Избербаш","region":"Республика Дагестан","size":56301},{"title":"Изобильный","region":"Ставропольский край","size":40546},{"title":"Иланский","region":"Красноярский край","size":16108},{"title":"Инза","region":"Ульяновская область","size":18547},{"title":"Инкерман","region":"Севастополь","size":11526},{"title":"Иннополис","region":"Республика Татарстан","size":96},{"title":"Инсар","region":"Республика Мордовия","size":8687},{"title":"Инта","region":"Республика Коми","size":32021},{"title":"Ипатово","region":"Ставропольский край","size":26055},{"title":"Ирбит","region":"Свердловская область","size":38352},{"title":"Иркутск","region":"Иркутская область","size":587225},{"title":"Исилькуль","region":"Омская область","size":25905},{"title":"Искитим","region":"Новосибирская область","size":60072},{"title":"Истра","region":"Московская область","size":35106},{"title":"Ишим","region":"Тюменская область","size":69567},{"title":"Ишимбай","region":"Республика Башкортостан","size":66259},{"title":"Йошкар-Ола","region":"Республика Марий Эл","size":248688},{"title":"Кадников","region":"Вологодская область","size":4797},{"title":"Казань","region":"Республика Татарстан","size":1216965,"stations":["Авиастроиельная","Аметьево","Горки","Козья слобода","Кремлевская","Площадь Габдуллы Тукая","Проспект Победы","Северный вокзал","Суконная слобода","Яшьлек"]},{"title":"Калач","region":"Воронежская область","size":20046},{"title":"Калач-на-Дону","region":"Волгоградская область","size":26892},{"title":"Калачинск","region":"Омская область","size":24000},{"title":"Калининград","region":"Калининградская область","size":431491},{"title":"Калининск","region":"Саратовская область","size":16442},{"title":"Калтан","region":"Кемеровская область","size":21893},{"title":"Калуга","region":"Калужская область","size":325185},{"title":"Калязин","region":"Тверская область","size":13870},{"title":"Камбарка","region":"Республика Удмуртия","size":11028},{"title":"Каменка","region":"Пензенская область","size":39579},{"title":"Каменногорск","region":"Ленинградская область","size":6761},{"title":"Каменск-Уральский","region":"Свердловская область","size":174710},{"title":"Каменск-Шахтинский","region":"Ростовская область","size":95306},{"title":"Камень-на-Оби","region":"Алтайский край","size":41787},{"title":"Камешково","region":"Владимирская область","size":13113},{"title":"Камызяк","region":"Астраханская область","size":16291},{"title":"Камышин","region":"Волгоградская область","size":119924},{"title":"Камышлов","region":"Свердловская область","size":26875},{"title":"Канаш","region":"Республика Чувашия","size":45608},{"title":"Кандалакша","region":"Мурманская область","size":35659},{"title":"Канск","region":"Красноярский край","size":94230},{"title":"Карабаново","region":"Владимирская область","size":14868},{"title":"Карабаш","region":"Челябинская область","size":13151},{"title":"Карабулак","region":"Республика Ингушетия","size":31081},{"title":"Карасук","region":"Новосибирская область","size":28929},{"title":"Карачаевск","region":"Республика Карачаево-Черкесия","size":23848},{"title":"Карачев","region":"Брянская область","size":19715},{"title":"Каргат","region":"Новосибирская область","size":10620},{"title":"Каргополь","region":"Архангельская область","size":10148},{"title":"Карпинск","region":"Свердловская область","size":29118},{"title":"Карталы","region":"Челябинская область","size":29136},{"title":"Касимов","region":"Рязанская область","size":33494},{"title":"Касли","region":"Челябинская область","size":16998},{"title":"Каспийск","region":"Республика Дагестан","size":103914},{"title":"Катав-Ивановск","region":"Челябинская область","size":17640},{"title":"Катайск","region":"Курганская область","size":14017},{"title":"Качканар","region":"Свердловская область","size":42563},{"title":"Кашин","region":"Тверская область","size":16174},{"title":"Кашира","region":"Московская область","size":41880},{"title":"Кедровый","region":"Томская область","size":2451},{"title":"Кемерово","region":"Кемеровская область","size":532884},{"title":"Кемь","region":"Республика Карелия","size":13061},{"title":"Керчь","region":"Республика Крым","size":144600},{"title":"Кизел","region":"Пермский край","size":20277},{"title":"Кизилюрт","region":"Республика Дагестан","size":36187},{"title":"Кизляр","region":"Республика Дагестан","size":49169},{"title":"Кимовск","region":"Тульская область","size":28493},{"title":"Кимры","region":"Тверская область","size":49623},{"title":"Кингисепп","region":"Ленинградская область","size":48667},{"title":"Кинель","region":"Самарская область","size":34472},{"title":"Кинешма","region":"Ивановская область","size":88113},{"title":"Киреевск","region":"Тульская область","size":25585},{"title":"Киренск","region":"Иркутская область","size":12652},{"title":"Киржач","region":"Владимирская область","size":30044},{"title":"Кириллов","region":"Вологодская область","size":7735},{"title":"Кириши","region":"Ленинградская область","size":52826},{"title":"Киров","region":"Калужская область","size":31888},{"title":"Киров","region":"Кировская область","size":473668},{"title":"Кировград","region":"Свердловская область","size":21959},{"title":"Кирово-Чепецк","region":"Кировская область","size":80920},{"title":"Кировск","region":"Ленинградская область","size":25633},{"title":"Кировск","region":"Мурманская область","size":28659},{"title":"Кирс","region":"Кировская область","size":10420},{"title":"Кирсанов","region":"Тамбовская область","size":17240},{"title":"Киселёвск","region":"Кемеровская область","size":98382},{"title":"Кисловодск","region":"Ставропольский край","size":128502},{"title":"Клин","region":"Московская область","size":80584},{"title":"Клинцы","region":"Брянская область","size":62510},{"title":"Княгинино","region":"Нижегородская область","size":6708},{"title":"Ковдор","region":"Мурманская область","size":18836},{"title":"Ковров","region":"Владимирская область","size":145492},{"title":"Ковылкино","region":"Республика Мордовия","size":21307},{"title":"Когалым","region":"Ханты-Мансийский АО — Югра","size":58192},{"title":"Кодинск","region":"Красноярский край","size":14835},{"title":"Козельск","region":"Калужская область","size":18203},{"title":"Козловка","region":"Республика Чувашия","size":10355},{"title":"Козьмодемьянск","region":"Республика Марий Эл","size":21262},{"title":"Кола","region":"Мурманская область","size":10447},{"title":"Кологрив","region":"Костромская область","size":3314},{"title":"Коломна","region":"Московская область","size":144642},{"title":"Колпашево","region":"Томская область","size":24126},{"title":"Кольчугино","region":"Владимирская область","size":45804},{"title":"Коммунар","region":"Ленинградская область","size":20265},{"title":"Комсомольск","region":"Ивановская область","size":8693},{"title":"Комсомольск-на-Амуре","region":"Хабаровский край","size":263906},{"title":"Конаково","region":"Тверская область","size":41303},{"title":"Кондопога","region":"Республика Карелия","size":32978},{"title":"Кондрово","region":"Калужская область","size":16672},{"title":"Константиновск","region":"Ростовская область","size":17926},{"title":"Копейск","region":"Челябинская область","size":137604},{"title":"Кораблино","region":"Рязанская область","size":12657},{"title":"Кореновск","region":"Краснодарский край","size":41179},{"title":"Коркино","region":"Челябинская область","size":38950},{"title":"Королёв","region":"Московская область","size":183452},{"title":"Короча","region":"Белгородская область","size":5877},{"title":"Корсаков","region":"Сахалинская область","size":33526},{"title":"Коряжма","region":"Архангельская область","size":39629},{"title":"Костерёво","region":"Владимирская область","size":9136},{"title":"Костомукша","region":"Республика Карелия","size":28433},{"title":"Кострома","region":"Костромская область","size":268617},{"title":"Котельники","region":"Московская область","size":32347},{"title":"Котельниково","region":"Волгоградская область","size":20441},{"title":"Котельнич","region":"Кировская область","size":24979},{"title":"Котлас","region":"Архангельская область","size":60562},{"title":"Котово","region":"Волгоградская область","size":24104},{"title":"Котовск","region":"Тамбовская область","size":31851},{"title":"Кохма","region":"Ивановская область","size":29408},{"title":"Красавино","region":"Вологодская область","size":7003},{"title":"Красноармейск","region":"Московская область","size":26294},{"title":"Красноармейск","region":"Саратовская область","size":24362},{"title":"Красновишерск","region":"Пермский край","size":17129},{"title":"Красногорск","region":"Московская область","size":116738},{"title":"Краснодар","region":"Краснодарский край","size":744933},{"title":"Краснозаводск","region":"Московская область","size":13432},{"title":"Краснознаменск","region":"Калининградская область","size":3522},{"title":"Краснознаменск","region":"Московская область","size":36057},{"title":"Краснокаменск","region":"Забайкальский край","size":55668},{"title":"Краснокамск","region":"Пермский край","size":52632},{"title":"Красноперекопск","region":"Республика Крым","size":29564},{"title":"Краснослободск","region":"Волгоградская область","size":16007},{"title":"Краснослободск","region":"Республика Мордовия","size":10151},{"title":"Краснотурьинск","region":"Свердловская область","size":59701},{"title":"Красноуральск","region":"Свердловская область","size":24973},{"title":"Красноуфимск","region":"Свердловская область","size":80457},{"title":"Красноярск","region":"Красноярский край","size":973826},{"title":"Красный Кут","region":"Саратовская область","size":14420},{"title":"Красный Сулин","region":"Ростовская область","size":40866},{"title":"Красный Холм","region":"Тверская область","size":5608},{"title":"Кремёнки","region":"Калужская область","size":11617},{"title":"Кропоткин","region":"Краснодарский край","size":80743},{"title":"Крымск","region":"Краснодарский край","size":57370},{"title":"Кстово","region":"Нижегородская область","size":66641},{"title":"Кубинка","region":"Московская область","size":22918},{"title":"Кувандык","region":"Оренбургская область","size":26176},{"title":"Кувшиново","region":"Тверская область","size":10008},{"title":"Кудымкар","region":"Пермский край","size":30711},{"title":"Кузнецк","region":"Пензенская область","size":88886},{"title":"Куйбышев","region":"Новосибирская область","size":47278},{"title":"Кулебаки","region":"Нижегородская область","size":35762},{"title":"Кумертау","region":"Республика Башкортостан","size":62854},{"title":"Кунгур","region":"Пермский край","size":67857},{"title":"Купино","region":"Новосибирская область","size":15448},{"title":"Курган","region":"Курганская область","size":333640},{"title":"Курганинск","region":"Краснодарский край","size":47974},{"title":"Курильск","region":"Сахалинская область","size":2070},{"title":"Курлово","region":"Владимирская область","size":6791},{"title":"Куровское","region":"Московская область","size":21821},{"title":"Курск","region":"Курская область","size":414595},{"title":"Куртамыш","region":"Курганская область","size":17098},{"title":"Курчатов","region":"Курская область","size":42691},{"title":"Куса","region":"Челябинская область","size":18792},{"title":"Кушва","region":"Свердловская область","size":33027},{"title":"Кызыл","region":"Республика Тыва","size":109906},{"title":"Кыштым","region":"Челябинская область","size":38950},{"title":"Кяхта","region":"Республика Бурятия","size":20013},{"title":"Лабинск","region":"Краснодарский край","size":62822},{"title":"Лабытнанги","region":"Ямало-Ненецкий АО","size":26948},{"title":"Лагань","region":"Республика Калмыкия","size":14323},{"title":"Ладушкин","region":"Калининградская область","size":3788},{"title":"Лаишево","region":"Республика Татарстан","size":7735},{"title":"Лакинск","region":"Владимирская область","size":15707},{"title":"Лангепас","region":"Ханты-Мансийский АО — Югра","size":41675},{"title":"Лахденпохья","region":"Республика Карелия","size":7818},{"title":"Лебедянь","region":"Липецкая область","size":20991},{"title":"Лениногорск","region":"Республика Татарстан","size":64145},{"title":"Ленинск","region":"Волгоградская область","size":15527},{"title":"Ленинск-Кузнецкий","region":"Кемеровская область","size":101666},{"title":"Ленск","region":"Республика Якутия","size":24955},{"title":"Лермонтов","region":"Ставропольский край","size":22540},{"title":"Лесной","region":"Свердловская область","size":52464},{"title":"Лесозаводск","region":"Приморский край","size":36975},{"title":"Лесосибирск","region":"Красноярский край","size":61146},{"title":"Ливны","region":"Орловская область","size":50430},{"title":"Ликино-Дулёво","region":"Московская область","size":31331},{"title":"Липецк","region":"Липецкая область","size":508124},{"title":"Липки","region":"Тульская область","size":8741},{"title":"Лиски","region":"Воронежская область","size":55864},{"title":"Лихославль","region":"Тверская область","size":12259},{"title":"Лобня","region":"Московская область","size":74350},{"title":"Лодейное Поле","region":"Ленинградская область","size":21053},{"title":"Лосино-Петровский","region":"Московская область","size":22550},{"title":"Луга","region":"Ленинградская область","size":36409},{"title":"Луза","region":"Кировская область","size":11262},{"title":"Лукоянов","region":"Нижегородская область","size":14949},{"title":"Луховицы","region":"Московская область","size":29849},{"title":"Лысково","region":"Нижегородская область","size":21882},{"title":"Лысьва","region":"Пермский край","size":67712},{"title":"Лыткарино","region":"Московская область","size":55147},{"title":"Льгов","region":"Курская область","size":21452},{"title":"Любань","region":"Ленинградская область","size":4188},{"title":"Люберцы","region":"Московская область","size":171978},{"title":"Любим","region":"Ярославская область","size":5553},{"title":"Людиново","region":"Калужская область","size":40550},{"title":"Лянтор","region":"Ханты-Мансийский АО — Югра","size":38922},{"title":"Магадан","region":"Магаданская область","size":95925},{"title":"Магас","region":"Республика Ингушетия","size":2505},{"title":"Магнитогорск","region":"Челябинская область","size":408401},{"title":"Майкоп","region":"Республика Адыгея","size":144055},{"title":"Майский","region":"Республика Кабардино-Балкария","size":26755},{"title":"Макаров","region":"Сахалинская область","size":6788},{"title":"Макарьев","region":"Костромская область","size":7114},{"title":"Макушино","region":"Курганская область","size":8337},{"title":"Малая Вишера","region":"Новгородская область","size":12461},{"title":"Малгобек","region":"Республика Ингушетия","size":31076},{"title":"Малмыж","region":"Кировская область","size":8265},{"title":"Малоархангельск","region":"Орловская область","size":3872},{"title":"Малоярославец","region":"Калужская область","size":30401},{"title":"Мамадыш","region":"Республика Татарстан","size":14432},{"title":"Мамоново","region":"Калининградская область","size":7757},{"title":"Мантурово","region":"Костромская область","size":17479},{"title":"Мариинск","region":"Кемеровская область","size":40522},{"title":"Мариинский Посад","region":"Республика Чувашия","size":10186},{"title":"Маркс","region":"Саратовская область","size":31535},{"title":"Махачкала","region":"Республика Дагестан","size":577990},{"title":"Мглин","region":"Брянская область","size":7916},{"title":"Мегион","region":"Ханты-Мансийский АО — Югра","size":49471},{"title":"Медвежьегорск","region":"Республика Карелия","size":15536},{"title":"Медногорск","region":"Оренбургская область","size":27253},{"title":"Медынь","region":"Калужская область","size":8298},{"title":"Межгорье","region":"Республика Башкортостан","size":17353},{"title":"Междуреченск","region":"Кемеровская область","size":101995},{"title":"Мезень","region":"Архангельская область","size":3599},{"title":"Меленки","region":"Владимирская область","size":15208},{"title":"Мелеуз","region":"Республика Башкортостан","size":61408},{"title":"Менделеевск","region":"Республика Татарстан","size":22075},{"title":"Мензелинск","region":"Республика Татарстан","size":16474},{"title":"Мещовск","region":"Калужская область","size":4101},{"title":"Миасс","region":"Челябинская область","size":151812},{"title":"Микунь","region":"Республика Коми","size":10732},{"title":"Миллерово","region":"Ростовская область","size":36493},{"title":"Минеральные Воды","region":"Ставропольский край","size":76715},{"title":"Минусинск","region":"Красноярский край","size":71171},{"title":"Миньяр","region":"Челябинская область","size":10195},{"title":"Мирный","region":"Республика Якутия","size":37179},{"title":"Мирный","region":"Архангельская область","size":30259},{"title":"Михайлов","region":"Рязанская область","size":11783},{"title":"Михайловка","region":"Волгоградская область","size":59153},{"title":"Михайловск","region":"Свердловская область","size":9215},{"title":"Михайловск","region":"Ставропольский край","size":71018},{"title":"Мичуринск","region":"Тамбовская область","size":98758},{"title":"Могоча","region":"Забайкальский край","size":13228},{"title":"Можайск","region":"Московская область","size":31388},{"title":"Можга","region":"Республика Удмуртия","size":47959},{"title":"Моздок","region":"Республика Северная Осетия - Алания","size":38748},{"title":"Мончегорск","region":"Мурманская область","size":45381},{"title":"Морозовск","region":"Ростовская область","size":27644},{"title":"Моршанск","region":"Тамбовская область","size":41550},{"title":"Мосальск","region":"Калужская область","size":4285},{"title":"Москва","region":"Москва","size":11514330,"stations":["Авиамоторная","Автозаводская","Академическая","Александровский сад","Алексеевская","Алма-Атинская","Алтуфьево","Аннино","Арбатская","Аэропорт","Б-р Адмирала Ушакова","Б-р Дмитрия Донского","Бабушкинская","Багратионовская","Баррикадная","Бауманская","Беговая","Белорусская","Беляево","Бибирево","Библиотека им.Ленина","Борисово","Боровицкая","Ботанический сад","Братиславская","Бунинская аллея","Варшавская","ВДНХ","Владыкино","Водный стадион","Войковская","Волгоградский пр-т","Волжская","Волоколамская","Воробьевы горы","Выставочная","Выхино","Динамо","Дмитровская","Добрынинская","Домодедовская","Достоевская","Дубровка","Жулебино","Зябликово","Измайловская","Калужская","Кантемировская","Каховская","Каширская","Киевская","Китай-город","Кожуховская","Коломенская","Комсомольская","Коньково","Красногвардейская","Краснопресненская","Красносельская","Красные ворота","Крестьянская застава","Кропоткинская","Крылатское","Кузнецкий мост","Кузьминки","Кунцевская","Курская","Кутузовская","Ленинский пр-т","Лермонтовский пр-т","Лубянка","Люблино","Марксистская","Марьина роща","Марьино","Маяковская","Медведково","Международная","Менделеевская","Митино","Молодежная","Мякинино","Нагатинская","Нагорная","Нахимовский пр-т","Новогиреево","Новокосино","Новокузнецкая","Новослободская","Новоясеневская","Новые Черемушки","Октябрьская","Октябрьское поле","Орехово","Отрадное","Охотный ряд","Павелецкая","Парк культуры","Парк Победы","Партизанская","Первомайская","Перово","Петровско-Разумовская","Печатники","Пионерская","Пл.Ильича","Планерная","Площадь Революции","Полежаевская","Полянка","Пр-т Вернадского","Пр-т Мира","Пражская","Преображенская пл.","Пролетарская","Профсоюзная","Пушкинская","Пятницкое шоссе","Речной вокзал","Рижская","Римская","Рязанский пр-т","Савеловская","Свиблово","Севастопольская","Семеновская","Серпуховская","Славянский бульвар","Смоленская","Сокол","Сокольники","Спортивная","Сретенский б-р","Строгино","Студенческая","Сухаревская","Сходненская","Таганская","Тверская","Театральная","Текстильщики","Теплый Стан","Тимирязевская","Третьяковская","Трубная","Тульская","Тургеневская","Тушинская","Ул.Академика Янгеля","Ул.Горчакова","Ул.Подбельского","Ул.Скобелевская","Ул.Старокачаловская","Улица 1905 года","Университет","Филевский парк","Фили","Фрунзенская","Царицыно","Цветной б-р","Черкизовская","Чертановская","Чеховская","Чистые пруды","Чкаловская","Ш.Энтузиастов","Шаболовская","Шипиловская","Щелковская","Щукинская","Электрозаводская","Юго-Западная","Южная","Ясенево"]},{"title":"Муравленко","region":"Ямало-Ненецкий АО","size":33401},{"title":"Мураши","region":"Кировская область","size":6752},{"title":"Мурманск","region":"Мурманская область","size":307664},{"title":"Муром","region":"Владимирская область","size":116078},{"title":"Мценск","region":"Орловская область","size":43216},{"title":"Мыски","region":"Кемеровская область","size":43029},{"title":"Мытищи","region":"Московская область","size":173341},{"title":"Мышкин","region":"Ярославская область","size":5932},{"title":"Набережные Челны","region":"Республика Татарстан","size":513242},{"title":"Навашино","region":"Нижегородская область","size":16413},{"title":"Наволоки","region":"Ивановская область","size":10207},{"title":"Надым","region":"Ямало-Ненецкий АО","size":46550},{"title":"Назарово","region":"Красноярский край","size":52829},{"title":"Назрань","region":"Республика Ингушетия","size":93357},{"title":"Называевск","region":"Омская область","size":12119},{"title":"Нальчик","region":"Республика Кабардино-Балкария","size":240095},{"title":"Нариманов","region":"Астраханская область","size":11386},{"title":"Наро-Фоминск","region":"Московская область","size":64640},{"title":"Нарткала","region":"Республика Кабардино-Балкария","size":31679},{"title":"Нарьян-Мар","region":"Ненецкий АО","size":21296},{"title":"Находка","region":"Приморский край","size":159695},{"title":"Невель","region":"Псковская область","size":16324},{"title":"Невельск","region":"Сахалинская область","size":11682},{"title":"Невинномысск","region":"Ставропольский край","size":118351},{"title":"Невьянск","region":"Свердловская область","size":25147},{"title":"Нелидово","region":"Тверская область","size":22886},{"title":"Неман","region":"Калининградская область","size":11794},{"title":"Нерехта","region":"Костромская область","size":22817},{"title":"Нерчинск","region":"Забайкальский край","size":14976},{"title":"Нерюнгри","region":"Республика Якутия","size":61746},{"title":"Нестеров","region":"Калининградская область","size":4584},{"title":"Нефтегорск","region":"Самарская область","size":18732},{"title":"Нефтекамск","region":"Республика Башкортостан","size":121757},{"title":"Нефтекумск","region":"Ставропольский край","size":27700},{"title":"Нефтеюганск","region":"Ханты-Мансийский АО — Югра","size":123276},{"title":"Нея","region":"Костромская область","size":9827},{"title":"Нижневартовск","region":"Ханты-Мансийский АО — Югра","size":251860},{"title":"Нижнекамск","region":"Республика Татарстан","size":234108},{"title":"Нижнеудинск","region":"Иркутская область","size":37056},{"title":"Нижние Серги","region":"Свердловская область","size":11217},{"title":"Нижний Ломов","region":"Пензенская область","size":22678},{"title":"Нижний Новгород","region":"Нижегородская область","size":1250615,"stations":["Автозаводская","Буревестник","Бурнаковская","Горьковская","Двигатель Революции","Заречная","Канавинская","Кировская","Комсомольская","Ленинская","Московская","Парк Культуры","Пролетарская","Чкаловская"]},{"title":"Нижний Тагил","region":"Свердловская область","size":361883},{"title":"Нижняя Салда","region":"Свердловская область","size":17969},{"title":"Нижняя Тура","region":"Свердловская область","size":21596},{"title":"Николаевск","region":"Волгоградская область","size":15081},{"title":"Николаевск-на-Амуре","region":"Хабаровский край","size":22773},{"title":"Никольск","region":"Вологодская область","size":8515},{"title":"Никольск","region":"Пензенская область","size":22471},{"title":"Никольское","region":"Ленинградская область","size":19345},{"title":"Новая Ладога","region":"Ленинградская область","size":8890},{"title":"Новая Ляля","region":"Свердловская область","size":12400},{"title":"Новоалександровск","region":"Ставропольский край","size":26759},{"title":"Новоалтайск","region":"Алтайский край","size":73134},{"title":"Новоаннинский","region":"Волгоградская область","size":17911},{"title":"Нововоронеж","region":"Воронежская область","size":32635},{"title":"Новодвинск","region":"Архангельская область","size":40612},{"title":"Новозыбков","region":"Брянская область","size":40552},{"title":"Новокубанск","region":"Краснодарский край","size":34847},{"title":"Новокузнецк","region":"Кемеровская область","size":547885},{"title":"Новокуйбышевск","region":"Самарская область","size":108449},{"title":"Новомичуринск","region":"Рязанская область","size":19309},{"title":"Новомосковск","region":"Тульская область","size":131227},{"title":"Новопавловск","region":"Ставропольский край","size":26556},{"title":"Новоржев","region":"Псковская область","size":3695},{"title":"Новороссийск","region":"Краснодарский край","size":241788},{"title":"Новосибирск","region":"Новосибирская область","size":1498921,"stations":["Березовая роща","Гагаринская","Заельцовская","Золотая нива","Красный пр-т","Маршала Покрышкина","Октябрьская","Площадь Гарина-Михайловского","Площадь Ленина","Площадь Маркса","Речной вокзал","Сибирская","Студенческая"]},{"title":"Новосиль","region":"Орловская область","size":3799},{"title":"Новосокольники","region":"Псковская область","size":8119},{"title":"Новотроицк","region":"Оренбургская область","size":97914},{"title":"Новоузенск","region":"Саратовская область","size":17015},{"title":"Новоульяновск","region":"Ульяновская область","size":16032},{"title":"Новоуральск","region":"Свердловская область","size":91813},{"title":"Новохопёрск","region":"Воронежская область","size":6849},{"title":"Новочебоксарск","region":"Республика Чувашия","size":124094},{"title":"Новочеркасск","region":"Ростовская область","size":169039},{"title":"Новошахтинск","region":"Ростовская область","size":111087},{"title":"Новый Оскол","region":"Белгородская область","size":19530},{"title":"Новый Уренгой","region":"Ямало-Ненецкий АО","size":104144},{"title":"Ногинск","region":"Московская область","size":99762},{"title":"Нолинск","region":"Кировская область","size":9556},{"title":"Норильск","region":"Красноярский край","size":175301},{"title":"Ноябрьск","region":"Ямало-Ненецкий АО","size":110572},{"title":"Нурлат","region":"Республика Татарстан","size":32600},{"title":"Нытва","region":"Пермский край","size":19041},{"title":"Нюрба","region":"Республика Якутия","size":10156},{"title":"Нягань","region":"Ханты-Мансийский АО — Югра","size":54903},{"title":"Нязепетровск","region":"Челябинская область","size":12452},{"title":"Няндома","region":"Архангельская область","size":22354},{"title":"Облучье","region":"Еврейская АО","size":9379},{"title":"Обнинск","region":"Калужская область","size":104798},{"title":"Обоянь","region":"Курская область","size":13562},{"title":"Обь","region":"Новосибирская область","size":26137},{"title":"Одинцово","region":"Московская область","size":139021},{"title":"Озёрск","region":"Калининградская область","size":4740},{"title":"Озёрск","region":"Челябинская область","size":82268},{"title":"Озёры","region":"Московская область","size":25788},{"title":"Октябрьск","region":"Самарская область","size":27244},{"title":"Октябрьский","region":"Республика Башкортостан","size":109379},{"title":"Окуловка","region":"Новгородская область","size":12464},{"title":"Олёкминск","region":"Республика Якутия","size":9487},{"title":"Оленегорск","region":"Мурманская область","size":23079},{"title":"Олонец","region":"Республика Карелия","size":9060},{"title":"Омск","region":"Омская область","size":1154000},{"title":"Омутнинск","region":"Кировская область","size":23618},{"title":"Онега","region":"Архангельская область","size":21359},{"title":"Опочка","region":"Псковская область","size":11601},{"title":"Орёл","region":"Орловская область","size":317854},{"title":"Оренбург","region":"Оренбургская область","size":570329},{"title":"Орехово-Зуево","region":"Московская область","size":120620},{"title":"Орлов","region":"Кировская область","size":6959},{"title":"Орск","region":"Оренбургская область","size":238006},{"title":"Оса","region":"Пермский край","size":22420},{"title":"Осинники","region":"Кемеровская область","size":45997},{"title":"Осташков","region":"Тверская область","size":18073},{"title":"Остров","region":"Псковская область","size":21670},{"title":"Островной","region":"Мурманская область","size":2177},{"title":"Острогожск","region":"Воронежская область","size":33842},{"title":"Отрадное","region":"Ленинградская область","size":23874},{"title":"Отрадный","region":"Самарская область","size":47709},{"title":"Оха","region":"Сахалинская область","size":23007},{"title":"Оханск","region":"Пермский край","size":7597},{"title":"Очёр","region":"Пермский край","size":15003},{"title":"Павлово","region":"Нижегородская область","size":60699},{"title":"Павловск","region":"Воронежская область","size":25126},{"title":"Павловский Посад","region":"Московская область","size":63771},{"title":"Палласовка","region":"Волгоградская область","size":15984},{"title":"Партизанск","region":"Приморский край","size":38648},{"title":"Певек","region":"Чукотский АО","size":4161},{"title":"Пенза","region":"Пензенская область","size":519592},{"title":"Первомайск","region":"Нижегородская область","size":14567},{"title":"Первоуральск","region":"Свердловская область","size":149800},{"title":"Перевоз","region":"Нижегородская область","size":9201},{"title":"Пересвет","region":"Московская область","size":14142},{"title":"Переславль-Залесский","region":"Ярославская область","size":41923},{"title":"Пермь","region":"Пермский край","size":1000679},{"title":"Пестово","region":"Новгородская область","size":15911},{"title":"Петров Вал","region":"Волгоградская область","size":13264},{"title":"Петровск","region":"Саратовская область","size":31158},{"title":"Петровск-Забайкальский","region":"Забайкальский край","size":18555},{"title":"Петрозаводск","region":"Республика Карелия","size":263540},{"title":"Петропавловск-Камчатский","region":"Камчатский край","size":179526},{"title":"Петухово","region":"Курганская область","size":11291},{"title":"Петушки","region":"Владимирская область","size":15167},{"title":"Печора","region":"Республика Коми","size":43458},{"title":"Печоры","region":"Псковская область","size":12308},{"title":"Пикалёво","region":"Ленинградская область","size":21567},{"title":"Пионерский","region":"Калининградская область","size":11017},{"title":"Питкяранта","region":"Республика Карелия","size":11484},{"title":"Плавск","region":"Тульская область","size":16248},{"title":"Пласт","region":"Челябинская область","size":17344},{"title":"Плёс","region":"Ивановская область","size":2341},{"title":"Поворино","region":"Воронежская область","size":17692},{"title":"Подольск","region":"Московская область","size":187956},{"title":"Подпорожье","region":"Ленинградская область","size":18729},{"title":"Покачи","region":"Ханты-Мансийский АО — Югра","size":17053},{"title":"Покров","region":"Владимирская область","size":17762},{"title":"Покровск","region":"Республика Якутия","size":9495},{"title":"Полевской","region":"Свердловская область","size":64316},{"title":"Полесск","region":"Калининградская область","size":7580},{"title":"Полысаево","region":"Кемеровская область","size":27624},{"title":"Полярные Зори","region":"Мурманская область","size":15106},{"title":"Полярный","region":"Мурманская область","size":17304},{"title":"Поронайск","region":"Сахалинская область","size":16461},{"title":"Порхов","region":"Псковская область","size":10608},{"title":"Похвистнево","region":"Самарская область","size":28181},{"title":"Почеп","region":"Брянская область","size":17933},{"title":"Починок","region":"Смоленская область","size":8776},{"title":"Пошехонье","region":"Ярославская область","size":6085},{"title":"Правдинск","region":"Калининградская область","size":4323},{"title":"Приволжск","region":"Ивановская область","size":16749},{"title":"Приморск","region":"Калининградская область","size":1956},{"title":"Приморск","region":"Ленинградская область","size":6122},{"title":"Приморско-Ахтарск","region":"Краснодарский край","size":32253},{"title":"Приозерск","region":"Ленинградская область","size":18929},{"title":"Прокопьевск","region":"Кемеровская область","size":210150},{"title":"Пролетарск","region":"Ростовская область","size":20267},{"title":"Протвино","region":"Московская область","size":37308},{"title":"Прохладный","region":"Республика Кабардино-Балкария","size":59595},{"title":"Псков","region":"Псковская область","size":203974},{"title":"Пугачёв","region":"Саратовская область","size":41705},{"title":"Пудож","region":"Республика Карелия","size":9698},{"title":"Пустошка","region":"Псковская область","size":4619},{"title":"Пучеж","region":"Ивановская область","size":8583},{"title":"Пушкино","region":"Московская область","size":102840},{"title":"Пущино","region":"Московская область","size":20263},{"title":"Пыталово","region":"Псковская область","size":5826},{"title":"Пыть-Ях","region":"Ханты-Мансийский АО — Югра","size":41453},{"title":"Пятигорск","region":"Ставропольский край","size":142397},{"title":"Радужный","region":"Владимирская область","size":18212},{"title":"Радужный","region":"Ханты-Мансийский АО — Югра","size":43394},{"title":"Райчихинск","region":"Амурская область","size":20499},{"title":"Раменское","region":"Московская область","size":96355},{"title":"Рассказово","region":"Тамбовская область","size":45484},{"title":"Ревда","region":"Свердловская область","size":61713},{"title":"Реж","region":"Свердловская область","size":38709},{"title":"Реутов","region":"Московская область","size":87195},{"title":"Ржев","region":"Тверская область","size":62026},{"title":"Родники","region":"Ивановская область","size":26318},{"title":"Рославль","region":"Смоленская область","size":54898},{"title":"Россошь","region":"Воронежская область","size":62865},{"title":"Ростов-на-Дону","region":"Ростовская область","size":1091544},{"title":"Ростов","region":"Ярославская область","size":31791},{"title":"Рошаль","region":"Московская область","size":21265},{"title":"Ртищево","region":"Саратовская область","size":41295},{"title":"Рубцовск","region":"Алтайский край","size":146386},{"title":"Рудня","region":"Смоленская область","size":10029},{"title":"Руза","region":"Московская область","size":13495},{"title":"Рузаевка","region":"Республика Мордовия","size":47529},{"title":"Рыбинск","region":"Ярославская область","size":200771},{"title":"Рыбное","region":"Рязанская область","size":18378},{"title":"Рыльск","region":"Курская область","size":15667},{"title":"Ряжск","region":"Рязанская область","size":21676},{"title":"Рязань","region":"Рязанская область","size":525062},{"title":"Саки","region":"Республика Крым","size":23400},{"title":"Салават","region":"Республика Башкортостан","size":156085},{"title":"Салаир","region":"Кемеровская область","size":8263},{"title":"Салехард","region":"Ямало-Ненецкий АО","size":42494},{"title":"Сальск","region":"Ростовская область","size":61312},{"title":"Самара","region":"Самарская область","size":1164900,"stations":["Безымянка","Гагаринская","Кировская","Московская","Победа","Российская","Советская","Спортивная","Юнгородок"]},{"title":"Санкт-Петербург","region":"Санкт-Петербург","size":4848742,"stations":["Автово","Адмиралтейская","Академическая","Балтийская","Бухарестская","Василеостровская","Владимирская","Волковская","Выборгская","Горьковская","Гостиный двор","Гражданский пр-т","Девяткино","Достоевская","Елизаровская","Звездная","Звенигородская","Кировский з-д","Комендантский пр-т","Крестовский остров","Купчино","Ладожская","Ленинский пр-т","Лесная","Лиговский пр-т","Ломоносовская","Маяковская","Международная","Московская","Московские ворота","Нарвская","Невский пр-т","Новочеркасская","Обводный канал","Обухово","Озерки","Парк Победы","Парнас","Петроградская","Пионерская","Пл. Александра Невского-1","Пл. Александра Невского-2","Пл. Восстания","Пл. Ленина","Пл. Мужества","Политехническая","Пр-т Большевиков","Пр-т Ветеранов","Пр-т Просвещения","Приморская","Пролетарская","Пушкинская","Рыбацкое","Садовая","Сенная Пл.","Спасская","Спортивная","Старая Деревня","Технологический ин-т","Удельная","Ул. Дыбенко","Фрунзенская","Черная речка","Чернышевская","Чкаловская","Электросила"]},{"title":"Саранск","region":"Республика Мордовия","size":297425},{"title":"Сарапул","region":"Республика Удмуртия","size":101390},{"title":"Саратов","region":"Саратовская область","size":836900},{"title":"Саров","region":"Нижегородская область","size":92073},{"title":"Сасово","region":"Рязанская область","size":28117},{"title":"Сатка","region":"Челябинская область","size":45465},{"title":"Сафоново","region":"Смоленская область","size":46116},{"title":"Саяногорск","region":"Республика Хакасия","size":49889},{"title":"Саянск","region":"Иркутская область","size":40786},{"title":"Светлогорск","region":"Калининградская область","size":10775},{"title":"Светлоград","region":"Ставропольский край","size":38520},{"title":"Светлый","region":"Калининградская область","size":21380},{"title":"Светогорск","region":"Ленинградская область","size":15973},{"title":"Свирск","region":"Иркутская область","size":13649},{"title":"Свободный","region":"Амурская область","size":58594},{"title":"Себеж","region":"Псковская область","size":6375},{"title":"Севастополь","region":"Севастополь","size":344479},{"title":"Северо-Курильск","region":"Сахалинская область","size":2381},{"title":"Северобайкальск","region":"Республика Бурятия","size":23673},{"title":"Северодвинск","region":"Архангельская область","size":192265},{"title":"Североморск","region":"Мурманская область","size":50076},{"title":"Североуральск","region":"Свердловская область","size":29279},{"title":"Северск","region":"Томская область","size":108466},{"title":"Севск","region":"Брянская область","size":7282},{"title":"Сегежа","region":"Республика Карелия","size":29660},{"title":"Сельцо","region":"Брянская область","size":17933},{"title":"Семёнов","region":"Нижегородская область","size":24472},{"title":"Семикаракорск","region":"Ростовская область","size":23884},{"title":"Семилуки","region":"Воронежская область","size":26025},{"title":"Сенгилей","region":"Ульяновская область","size":6959},{"title":"Серафимович","region":"Волгоградская область","size":9368},{"title":"Сергач","region":"Нижегородская область","size":21387},{"title":"Сергиев Посад","region":"Московская область","size":110878},{"title":"Сердобск","region":"Пензенская область","size":35393},{"title":"Серов","region":"Свердловская область","size":99381},{"title":"Серпухов","region":"Московская область","size":126496},{"title":"Сертолово","region":"Ленинградская область","size":47854},{"title":"Сибай","region":"Республика Башкортостан","size":62732},{"title":"Сим","region":"Челябинская область","size":14465},{"title":"Симферополь","region":"Республика Крым","size":362366},{"title":"Сковородино","region":"Амурская область","size":9561},{"title":"Скопин","region":"Рязанская область","size":30374},{"title":"Славгород","region":"Алтайский край","size":30370},{"title":"Славск","region":"Калининградская область","size":4614},{"title":"Славянск-на-Кубани","region":"Краснодарский край","size":63768},{"title":"Сланцы","region":"Ленинградская область","size":33587},{"title":"Слободской","region":"Кировская область","size":33983},{"title":"Слюдянка","region":"Иркутская область","size":18542},{"title":"Смоленск","region":"Смоленская область","size":326863},{"title":"Снежинск","region":"Челябинская область","size":48896},{"title":"Снежногорск","region":"Мурманская область","size":12698},{"title":"Собинка","region":"Владимирская область","size":19482},{"title":"Советск","region":"Калининградская область","size":41709},{"title":"Советск","region":"Кировская область","size":16592},{"title":"Советск","region":"Тульская область","size":7537},{"title":"Советская Гавань","region":"Хабаровский край","size":27712},{"title":"Советский","region":"Ханты-Мансийский АО — Югра","size":26434},{"title":"Сокол","region":"Вологодская область","size":38454},{"title":"Солигалич","region":"Костромская область","size":6438},{"title":"Соликамск","region":"Пермский край","size":97239},{"title":"Солнечногорск","region":"Московская область","size":52996},{"title":"Соль-Илецк","region":"Оренбургская область","size":26308},{"title":"Сольвычегодск","region":"Архангельская область","size":2460},{"title":"Сольцы","region":"Новгородская область","size":10317},{"title":"Сорочинск","region":"Оренбургская область","size":30136},{"title":"Сорск","region":"Республика Хакасия","size":12140},{"title":"Сортавала","region":"Республика Карелия","size":19215},{"title":"Сосенский","region":"Калужская область","size":12394},{"title":"Сосновка","region":"Кировская область","size":11960},{"title":"Сосновоборск","region":"Красноярский край","size":33090},{"title":"Сосновый Бор","region":"Ленинградская область","size":65901},{"title":"Сосногорск","region":"Республика Коми","size":27809},{"title":"Сочи","region":"Краснодарский край","size":343285},{"title":"Спас-Деменск","region":"Калужская область","size":4904},{"title":"Спас-Клепики","region":"Рязанская область","size":5917},{"title":"Спасск","region":"Пензенская область","size":7442},{"title":"Спасск-Дальний","region":"Приморский край","size":44166},{"title":"Спасск-Рязанский","region":"Рязанская область","size":7745},{"title":"Среднеколымск","region":"Республика Якутия","size":3525},{"title":"Среднеуральск","region":"Свердловская область","size":20357},{"title":"Сретенск","region":"Забайкальский край","size":6850},{"title":"Ставрополь","region":"Ставропольский край","size":398266},{"title":"Старая Купавна","region":"Московская область","size":21859},{"title":"Старая Русса","region":"Новгородская область","size":32235},{"title":"Старица","region":"Тверская область","size":8610},{"title":"Стародуб","region":"Брянская область","size":19010},{"title":"Старый Крым","region":"Республика Крым","size":9485},{"title":"Старый Оскол","region":"Белгородская область","size":221163},{"title":"Стерлитамак","region":"Республика Башкортостан","size":273432},{"title":"Стрежевой","region":"Томская область","size":42216},{"title":"Строитель","region":"Белгородская область","size":23933},{"title":"Струнино","region":"Владимирская область","size":14372},{"title":"Ступино","region":"Московская область","size":66942},{"title":"Суворов","region":"Тульская область","size":18975},{"title":"Судак","region":"Республика Крым","size":15368},{"title":"Суджа","region":"Курская область","size":6036},{"title":"Судогда","region":"Владимирская область","size":11848},{"title":"Суздаль","region":"Владимирская область","size":10535},{"title":"Суоярви","region":"Республика Карелия","size":9763},{"title":"Сураж","region":"Брянская область","size":11640},{"title":"Сургут","region":"Ханты-Мансийский АО — Югра","size":306703},{"title":"Суровикино","region":"Волгоградская область","size":20527},{"title":"Сурск","region":"Пензенская область","size":7032},{"title":"Сусуман","region":"Магаданская область","size":5865},{"title":"Сухиничи","region":"Калужская область","size":16295},{"title":"Сухой Лог","region":"Свердловская область","size":34836},{"title":"Сызрань","region":"Самарская область","size":178773},{"title":"Сыктывкар","region":"Республика Коми","size":235006},{"title":"Сысерть","region":"Свердловская область","size":20594},{"title":"Сычёвка","region":"Смоленская область","size":8111},{"title":"Сясьстрой","region":"Ленинградская область","size":13747},{"title":"Тавда","region":"Свердловская область","size":35421},{"title":"Таганрог","region":"Ростовская область","size":257692},{"title":"Тайга","region":"Кемеровская область","size":25330},{"title":"Тайшет","region":"Иркутская область","size":35481},{"title":"Талдом","region":"Московская область","size":13819},{"title":"Талица","region":"Свердловская область","size":18339},{"title":"Тамбов","region":"Тамбовская область","size":280457},{"title":"Тара","region":"Омская область","size":26664},{"title":"Тарко-Сале","region":"Ямало-Ненецкий АО","size":20372},{"title":"Таруса","region":"Калужская область","size":9656},{"title":"Татарск","region":"Новосибирская область","size":26114},{"title":"Таштагол","region":"Кемеровская область","size":23114},{"title":"Тверь","region":"Тверская область","size":403726},{"title":"Теберда","region":"Республика Карачаево-Черкесия","size":9097},{"title":"Тейково","region":"Ивановская область","size":34993},{"title":"Темников","region":"Республика Мордовия","size":7247},{"title":"Темрюк","region":"Краснодарский край","size":38014},{"title":"Терек","region":"Республика Кабардино-Балкария","size":19170},{"title":"Тетюши","region":"Республика Татарстан","size":11596},{"title":"Тимашёвск","region":"Краснодарский край","size":53921},{"title":"Тихвин","region":"Ленинградская область","size":58843},{"title":"Тихорецк","region":"Краснодарский край","size":61825},{"title":"Тобольск","region":"Тюменская область","size":99698},{"title":"Тогучин","region":"Новосибирская область","size":21531},{"title":"Тольятти","region":"Самарская область","size":719484},{"title":"Томари","region":"Сахалинская область","size":4537},{"title":"Томмот","region":"Республика Якутия","size":8054},{"title":"Томск","region":"Томская область","size":522940},{"title":"Топки","region":"Кемеровская область","size":28642},{"title":"Торжок","region":"Тверская область","size":47702},{"title":"Торопец","region":"Тверская область","size":13018},{"title":"Тосно","region":"Ленинградская область","size":39127},{"title":"Тотьма","region":"Вологодская область","size":9784},{"title":"Трёхгорный","region":"Челябинская область","size":33678},{"title":"Троицк","region":"Челябинская область","size":78637},{"title":"Трубчевск","region":"Брянская область","size":15014},{"title":"Туапсе","region":"Краснодарский край","size":63233},{"title":"Туймазы","region":"Республика Башкортостан","size":66849},{"title":"Тула","region":"Тульская область","size":501129},{"title":"Тулун","region":"Иркутская область","size":44603},{"title":"Туран","region":"Республика Тыва","size":4988},{"title":"Туринск","region":"Свердловская область","size":17990},{"title":"Тутаев","region":"Ярославская область","size":41001},{"title":"Тында","region":"Амурская область","size":35574},{"title":"Тырныауз","region":"Республика Кабардино-Балкария","size":21000},{"title":"Тюкалинск","region":"Омская область","size":12050},{"title":"Тюмень","region":"Тюменская область","size":581758},{"title":"Уварово","region":"Тамбовская область","size":26829},{"title":"Циолковский","region":"Амурская область","size":6208},{"title":"Углегорск","region":"Сахалинская область","size":11880},{"title":"Углич","region":"Ярославская область","size":34505},{"title":"Удачный","region":"Республика Якутия","size":12611},{"title":"Удомля","region":"Тверская область","size":31048},{"title":"Ужур","region":"Красноярский край","size":16079},{"title":"Узловая","region":"Тульская область","size":55282},{"title":"Улан-Удэ","region":"Республика Бурятия","size":431922},{"title":"Ульяновск","region":"Ульяновская область","size":613793},{"title":"Унеча","region":"Брянская область","size":26196},{"title":"Урай","region":"Ханты-Мансийский АО — Югра","size":39435},{"title":"Урень","region":"Нижегородская область","size":12311},{"title":"Уржум","region":"Кировская область","size":10213},{"title":"Урус-Мартан","region":"Республика Чечня","size":49071},{"title":"Урюпинск","region":"Волгоградская область","size":41594},{"title":"Усинск","region":"Республика Коми","size":41100},{"title":"Усмань","region":"Липецкая область","size":18752},{"title":"Усолье-Сибирское","region":"Иркутская область","size":83364},{"title":"Усолье","region":"Пермский край","size":5694},{"title":"Уссурийск","region":"Приморский край","size":157946},{"title":"Усть-Джегута","region":"Республика Карачаево-Черкесия","size":30602},{"title":"Усть-Илимск","region":"Иркутская область","size":86591},{"title":"Усть-Катав","region":"Челябинская область","size":23586},{"title":"Усть-Кут","region":"Иркутская область","size":45061},{"title":"Усть-Лабинск","region":"Краснодарский край","size":43268},{"title":"Устюжна","region":"Вологодская область","size":9478},{"title":"Уфа","region":"Республика Башкортостан","size":1062300},{"title":"Ухта","region":"Республика Коми","size":99642},{"title":"Учалы","region":"Республика Башкортостан","size":37771},{"title":"Уяр","region":"Красноярский край","size":12666},{"title":"Фатеж","region":"Курская область","size":5404},{"title":"Феодосия","region":"Республика Крым","size":69786},{"title":"Фокино","region":"Брянская область","size":13874},{"title":"Фокино","region":"Приморский край","size":23683},{"title":"Фролово","region":"Волгоградская область","size":39489},{"title":"Фрязино","region":"Московская область","size":55449},{"title":"Фурманов","region":"Ивановская область","size":36149},{"title":"Хабаровск","region":"Хабаровский край","size":577668},{"title":"Хадыженск","region":"Краснодарский край","size":21580},{"title":"Ханты-Мансийск","region":"Ханты-Мансийский АО — Югра","size":79410},{"title":"Харабали","region":"Астраханская область","size":18209},{"title":"Харовск","region":"Вологодская область","size":10078},{"title":"Хасавюрт","region":"Республика Дагестан","size":133929},{"title":"Хвалынск","region":"Саратовская область","size":13199},{"title":"Хилок","region":"Забайкальский край","size":11530},{"title":"Химки","region":"Московская область","size":207125},{"title":"Холм","region":"Новгородская область","size":3829},{"title":"Холмск","region":"Сахалинская область","size":30936},{"title":"Хотьково","region":"Московская область","size":21612},{"title":"Цивильск","region":"Республика Чувашия","size":13478},{"title":"Цимлянск","region":"Ростовская область","size":15029},{"title":"Чадан","region":"Республика Тыва","size":9037},{"title":"Чайковский","region":"Пермский край","size":82933},{"title":"Чапаевск","region":"Самарская область","size":72689},{"title":"Чаплыгин","region":"Липецкая область","size":12656},{"title":"Чебаркуль","region":"Челябинская область","size":43405},{"title":"Чебоксары","region":"Республика Чувашия","size":447929},{"title":"Чегем","region":"Республика Кабардино-Балкария","size":17988},{"title":"Чекалин","region":"Тульская область","size":994},{"title":"Челябинск","region":"Челябинская область","size":1130273},{"title":"Чердынь","region":"Пермский край","size":4920},{"title":"Черемхово","region":"Иркутская область","size":52650},{"title":"Черепаново","region":"Новосибирская область","size":19346},{"title":"Череповец","region":"Вологодская область","size":312311},{"title":"Черкесск","region":"Республика Карачаево-Черкесия","size":121439},{"title":"Чёрмоз","region":"Пермский край","size":4017},{"title":"Черноголовка","region":"Московская область","size":20986},{"title":"Черногорск","region":"Республика Хакасия","size":72117},{"title":"Чернушка","region":"Пермский край","size":33275},{"title":"Черняховск","region":"Калининградская область","size":40464},{"title":"Чехов","region":"Московская область","size":60677},{"title":"Чистополь","region":"Республика Татарстан","size":60703},{"title":"Чита","region":"Забайкальский край","size":323964},{"title":"Чкаловск","region":"Нижегородская область","size":12371},{"title":"Чудово","region":"Новгородская область","size":16148},{"title":"Чулым","region":"Новосибирская область","size":11964},{"title":"Чусовой","region":"Пермский край","size":46740},{"title":"Чухлома","region":"Костромская область","size":5209},{"title":"Шагонар","region":"Республика Тыва","size":10958},{"title":"Шадринск","region":"Курганская область","size":77744},{"title":"Шали","region":"Республика Чечня","size":47715},{"title":"Шарыпово","region":"Красноярский край","size":38570},{"title":"Шарья","region":"Костромская область","size":23668},{"title":"Шатура","region":"Московская область","size":32836},{"title":"Шахты","region":"Ростовская область","size":240152},{"title":"Шахунья","region":"Нижегородская область","size":21337},{"title":"Шацк","region":"Рязанская область","size":6562},{"title":"Шебекино","region":"Белгородская область","size":44277},{"title":"Шелехов","region":"Иркутская область","size":47960},{"title":"Шенкурск","region":"Архангельская область","size":5702},{"title":"Шилка","region":"Забайкальский край","size":13947},{"title":"Шимановск","region":"Амурская область","size":19815},{"title":"Шиханы","region":"Саратовская область","size":6067},{"title":"Шлиссельбург","region":"Ленинградская область","size":13305},{"title":"Шумерля","region":"Республика Чувашия","size":33412},{"title":"Шумиха","region":"Курганская область","size":17821},{"title":"Шуя","region":"Ивановская область","size":58528},{"title":"Щёкино","region":"Тульская область","size":58154},{"title":"Щёлкино","region":"Республика Крым","size":11194},{"title":"Щёлково","region":"Московская область","size":110380},{"title":"Щигры","region":"Курская область","size":17043},{"title":"Щучье","region":"Курганская область","size":10971},{"title":"Электрогорск","region":"Московская область","size":22120},{"title":"Электросталь","region":"Московская область","size":155324},{"title":"Электроугли","region":"Московская область","size":20120},{"title":"Элиста","region":"Республика Калмыкия","size":103728},{"title":"Энгельс","region":"Саратовская область","size":202838},{"title":"Эртиль","region":"Воронежская область","size":11387},{"title":"Югорск","region":"Ханты-Мансийский АО — Югра","size":34066},{"title":"Южа","region":"Ивановская область","size":14170},{"title":"Южно-Сахалинск","region":"Сахалинская область","size":181727},{"title":"Южно-Сухокумск","region":"Республика Дагестан","size":10048},{"title":"Южноуральск","region":"Челябинская область","size":37890},{"title":"Юрга","region":"Кемеровская область","size":81536},{"title":"Юрьев-Польский","region":"Владимирская область","size":19588},{"title":"Юрьевец","region":"Ивановская область","size":10205},{"title":"Юрюзань","region":"Челябинская область","size":12568},{"title":"Юхнов","region":"Калужская область","size":7056},{"title":"Ядрин","region":"Республика Чувашия","size":9614},{"title":"Якутск","region":"Республика Якутия","size":269486},{"title":"Ялта","region":"Республика Крым","size":78040},{"title":"Ялуторовск","region":"Тюменская область","size":36494},{"title":"Янаул","region":"Республика Башкортостан","size":26988},{"title":"Яранск","region":"Кировская область","size":17252},{"title":"Яровое","region":"Алтайский край","size":18085},{"title":"Ярославль","region":"Ярославская область","size":591486},{"title":"Ярцево","region":"Смоленская область","size":47853},{"title":"Ясногорск","region":"Тульская область","size":16804},{"title":"Ясный","region":"Оренбургская область","size":16082},{"title":"Яхрома","region":"Московская область","size":13248}]